dynamicDQNet/__init__.py
dynamicDQNet/core.py
dynamicDQNet-0.3.0.dist-info/METADATA
dynamicDQNet-0.3.0.dist-info/WHEEL
dynamicDQNet-0.3.0.dist-info/top_level.txt
dynamicDQNet-0.3.0.dist-info/RECORD
